observer.py
pattern_observer-1.0.0.dist-info/METADATA
pattern_observer-1.0.0.dist-info/metadata.json
pattern_observer-1.0.0.dist-info/DESCRIPTION.rst
pattern_observer-1.0.0.dist-info/WHEEL
pattern_observer-1.0.0.dist-info/top_level.txt
pattern_observer-1.0.0.dist-info/RECORD
