Metadata-Version: 2.0
Name: pattern-observer
Version: 1.0.0
Summary: A observer pattern implementation in Python based on jQuery.
Home-page: https://github.com/fernandojunior/python-pattern-observer
Author: Fernando Felix do Nascimento Junior
Author-email: fernandojr.ifcg@live.com
License: MIT License
Keywords: observer design pattern
Platform: any
Classifier: Environment :: Web Environment
Classifier: Development Status :: 5 - Production/Stable
Classifier: Intended Audience :: Developers
Classifier: License :: OSI Approved :: MIT License
Classifier: Natural Language :: English
Classifier: Operating System :: OS Independent
Classifier: Programming Language :: Python :: 2
Classifier: Programming Language :: Python :: 2.6
Classifier: Programming Language :: Python :: 2.7
Classifier: Programming Language :: Python :: 3
Classifier: Programming Language :: Python :: 3.3
Classifier: Programming Language :: Python :: 3.4
Classifier: Programming Language :: Python :: 3.5
